examcard/__init__.py
examcard/examcard.py
examcard/sz_funcs.py
examcard/sz_sequence.py
tests/__init__.py
tests/conftest.py
tests/test_examcard.py
gt_examcard_parser-0.1.0.dist-info/LICENSE
gt_examcard_parser-0.1.0.dist-info/METADATA
gt_examcard_parser-0.1.0.dist-info/WHEEL
gt_examcard_parser-0.1.0.dist-info/top_level.txt
gt_examcard_parser-0.1.0.dist-info/RECORD
