Metadata-Version: 2.1
Name: gt-examcard-parser
Version: 0.1.0
Summary: Parser for Philips ExamCards
Home-page: https://github.com/gyrotools/gt-examcard-parser
Author: Martin Bührer
Author-email: info@gyrotools.com
Classifier: Programming Language :: Python :: 3
Classifier: License :: OSI Approved :: MIT License
Classifier: Operating System :: OS Independent
Requires-Python: >=3.6.0
License-File: LICENSE
